LICENSE.txt
MANIFEST.in
README.txt
RELEASE.txt
requirements.txt
requirements_dev.txt
setup.py
ask/__init__.py
ask/__init__.pyc
ask/admin.py
ask/admin.pyc
ask/api.py
ask/api.pyc
ask/forms.py
ask/forms.pyc
ask/lookups.py
ask/lookups.pyc
ask/tests.py
ask/urls.py
ask/urls.pyc
ask/urls_admin.py
ask/urls_admin.pyc
ask/utils.py
ask/utils.pyc
ask/validators.py
ask/validators.pyc
ask/yamlextras.py
ask/yamlextras.pyc
ask/fixtures/ask_test.json
ask/fixtures/asker_text.md
ask/fixtures/demonstration_asker.markdown
ask/migrations/0001_initial.py
ask/migrations/0002_auto__add_field_choiceset_yaml.py
ask/migrations/0003_auto__add_field_question_scoresheet.py
ask/migrations/0004_auto.py
ask/migrations/0005_auto__add_field_asker_finish_on_last_page.py
ask/migrations/0006_auto__add_field_choice_mapped_score.py
ask/migrations/0007_auto__del_field_question_score_mapping.py
ask/migrations/0008_auto__del_instrument__del_unique_instrument_name__del_field_question_d.py
ask/migrations/0009_auto__del_field_question_showif.py
ask/migrations/0010_auto__del_field_question_audio.py
ask/migrations/0010_auto__del_field_question_audio.pyc
ask/migrations/0011_auto__del_field_question_widget_kwargs__add_field_question_attrs.py
ask/migrations/0012_auto__add_field_asker_system_audio__del_field_question_attrs__add_fiel.py
ask/migrations/0013_auto__del_field_question_field_kwargs.py
ask/migrations/0014_auto__add_field_question_extra.py
ask/migrations/0015_convert_extra_attrs_to_yaml.py
ask/migrations/0016_auto__del_field_question_extra_attrs.py
ask/migrations/0017_auto__del_field_question_extra__add_field_question_extra_attrs.py
ask/migrations/0018_auto__add_field_askpage_randomise_questions.py
ask/migrations/__init__.py
ask/migrations/__init__.pyc
ask/models/__init__.py
ask/models/__init__.pyc
ask/models/asker.py
ask/models/asker.pyc
ask/models/custom_widgets.py
ask/models/custom_widgets.pyc
ask/models/fields.py
ask/models/fields.pyc
ask/models/page.py
ask/models/page.pyc
ask/models/parse_conditional.py
signalbox.egg-info/PKG-INFO
signalbox.egg-info/SOURCES.txt
signalbox.egg-info/dependency_links.txt
signalbox.egg-info/requires.txt
signalbox.egg-info/top_level.txt
