Metadata-Version: 1.0
Name: signalbox
Version: 0.3.4.4
Summary: Run longitudinal studies and randomised trials over the web and telephone.
Home-page: http://pypi.python.org/pypi/signalbox/
Author: Ben Whalley
Author-email: benwhalley@gmail.com
License: LICENSE.txt
Platform: UNKNOWN
